load_files/__init__.py
load_files/client.py
load_files/file_manager.py
load_files/search.py
load_files/vector_manager.py
file_management-1.0.8.dist-info/LICENSE
file_management-1.0.8.dist-info/METADATA
file_management-1.0.8.dist-info/WHEEL
file_management-1.0.8.dist-info/entry_points.txt
file_management-1.0.8.dist-info/top_level.txt
file_management-1.0.8.dist-info/RECORD
