Metadata-Version: 2.1
Name: file-management
Version: 1.0.8
Summary: Interacting with the Open AI API
Home-page: https://github.com/Cowgirl-AI/file-management
Author: Tera Earlywine
Author-email: dev@teraearlywine.com
Requires-Python: >=3.10
License-File: LICENSE
